{
  "schema_version": "1.0",
  "framework": "UCITS",
  "source": "Historical stress scenario library for UCITS monitoring",
  "scenario_type": "historical",
  "basis": "CSSF UCITS requirement for most relevant historical scenarios with holding period",
  "notes": "This is a temporary separate library from the HF scenario setup. It may later be merged into or replace the current scenario library once both UCITS and AIF historical scenario definitions are aligned.",
  "scenarios": {
    "historical_2008_black_week": {
      "test_category": "Historical",
      "scenario_name": "2008 Financial Crisis, hp=20d",
      "description": "Global Financial Crisis period capturing equity market crashes, credit spread widening, and FX volatility",
      "period": "September - December 2008",
      "holding_period_days": 20,
      "holding_period_basis": "CSSF UCITS reporting standard holding period for historical scenario calibration",
      "shocks": {
        "equity": {
          "shock": -0.4,
          "unit": "pct",
          "description": "Equity market decline"
        },
        "interest_rates": {
          "shock": -0.01,
          "unit": "pct",
          "description": "Parallel rate shift (negative in financial crisis)"
        },
        "credit_spreads": {
          "shock": 0.03,
          "unit": "pct",
          "description": "Credit spread widening"
        },
        "fx": {
          "shock_by_currency": {
            "USD": -0.05,
            "GBP": -0.15
          },
          "unit": "pct",
          "description": "FX movements against EUR"
        }
      },
      "regulatory_basis": "CSSF UCITS stress testing framework \u2014 most relevant historical scenario"
    },
    "historical_2020_covid": {
      "test_category": "Historical",
      "scenario_name": "2020 COVID-19 Crash, hp=20d",
      "description": "COVID-19 pandemic initial shock period with equity decline, credit widening, and FX volatility",
      "period": "February - March 2020",
      "holding_period_days": 20,
      "holding_period_basis": "CSSF UCITS reporting standard holding period for historical scenario calibration",
      "shocks": {
        "equity": {
          "shock": -0.3,
          "unit": "pct",
          "description": "Equity market decline"
        },
        "interest_rates": {
          "shock": -0.005,
          "unit": "pct",
          "description": "Parallel rate shift (rates cut in response)"
        },
        "credit_spreads": {
          "shock": 0.02,
          "unit": "pct",
          "description": "Credit spread widening"
        },
        "fx": {
          "shock_by_currency": {
            "USD": 0.05,
            "GBP": -0.05
          },
          "unit": "pct",
          "description": "FX movements against EUR (USD strength, GBP weakness)"
        }
      },
      "regulatory_basis": "CSSF UCITS stress testing framework \u2014 most relevant historical scenario"
    },
    "historical_2022_rate_inflation": {
      "test_category": "Historical",
      "scenario_name": "2022 Rate and Inflation Shock, hp=20d",
      "description": "Central bank rate hike cycle in response to inflation, with equity decline, rate increase, and spread widening",
      "period": "January - December 2022",
      "holding_period_days": 20,
      "holding_period_basis": "CSSF UCITS reporting standard holding period for historical scenario calibration",
      "shocks": {
        "equity": {
          "shock": -0.2,
          "unit": "pct",
          "description": "Equity market decline due to rising rates and growth concerns"
        },
        "interest_rates": {
          "shock": 0.03,
          "unit": "pct",
          "description": "Parallel rate shift (rates rising with inflation)"
        },
        "credit_spreads": {
          "shock": 0.015,
          "unit": "pct",
          "description": "Credit spread widening due to rising rates"
        },
        "fx": {
          "shock_by_currency": {
            "USD": 0.1,
            "GBP": -0.05
          },
          "unit": "pct",
          "description": "FX movements against EUR (USD strength from higher rates, GBP weakness)"
        }
      },
      "regulatory_basis": "CSSF UCITS stress testing framework \u2014 most relevant historical scenario"
    }
  }
}